{
  "total-app-time" : 1.73458,
  "total-kernel-time" : 0.113838,
  "total-non-kernel-time" : 1.62074,
  "percent-in-kernels" : 6.56284,
  "unique-kernel-calls" : 444,
  "region-data" : [
    {
      "kernel-name": "binary::read(path, comm, mesh, strict)",
      "call-count": 4,
      "total-time": 1.64713,
      "time-per-call": 0.411782,
      "kernel-type": "REGION"
    },
    {
      "kernel-name": "binary::read_in_comm(path, comm, mesh, version)",
      "call-count": 4,
      "total-time": 1.3444,
      "time-per-call": 0.336101,
      "kernel-type": "REGION"
    },
    {
      "kernel-name": "binary::read(istream, mesh, version)",
      "call-count": 4,
      "total-time": 1.33841,
      "time-per-call": 0.334602,
      "kernel-type": "REGION"
    },
    {
      "kernel-name": "exch",
      "call-count": 48,
      "total-time": 0.154263,
      "time-per-call": 0.0032138,
      "kernel-type": "REGION"
    },
    {
      "kernel-name": "Dist::exch",
      "call-count": 48,
      "total-time": 0.153984,
      "time-per-call": 0.00320801,
      "kernel-type": "REGION"
    },
    {
      "kernel-name": "Comm::alltoallv",
      "call-count": 48,
      "total-time": 0.142586,
      "time-per-call": 0.00297055,
      "kernel-type": "REGION"
    },
    {
      "kernel-name": "set_dest_ranks",
      "call-count": 12,
      "total-time": 0.128965,
      "time-per-call": 0.0107471,
      "kernel-type": "REGION"
    },
    {
      "kernel-name": "set_dest_idxs",
      "call-count": 12,
      "total-time": 0.102996,
      "time-per-call": 0.00858303,
      "kernel-type": "REGION"
    },
    {
      "kernel-name": "Neighbor_ialltoallv",
      "call-count": 48,
      "total-time": 0.0592089,
      "time-per-call": 0.00123352,
      "kernel-type": "REGION"
    },
    {
      "kernel-name": "meshField-sync",
      "call-count": 4,
      "total-time": 0.0574799,
      "time-per-call": 0.01437,
      "kernel-type": "REGION"
    },
    {
      "kernel-name": "sync_array",
      "call-count": 36,
      "total-time": 0.0570745,
      "time-per-call": 0.0015854,
      "kernel-type": "REGION"
    },
    {
      "kernel-name": "array host to device",
      "call-count": 148,
      "total-time": 0.0247688,
      "time-per-call": 0.000167357,
      "kernel-type": "REGION"
    },
    {
      "kernel-name": "sources_from_destinations",
      "call-count": 12,
      "total-time": 0.0117931,
      "time-per-call": 0.000982761,
      "kernel-type": "REGION"
    },
    {
      "kernel-name": "Write allocation",
      "call-count": 452,
      "total-time": 0.0113878,
      "time-per-call": 2.51943e-05,
      "kernel-type": "REGION"
    },
    {
      "kernel-name": "parallel_for",
      "call-count": 188,
      "total-time": 0.00796151,
      "time-per-call": 4.23485e-05,
      "kernel-type": "REGION"
    },
    {
      "kernel-name": "offset_scan",
      "call-count": 24,
      "total-time": 0.00535583,
      "time-per-call": 0.00022316,
      "kernel-type": "REGION"
    },
    {
      "kernel-name": "Neighbor_allgather",
      "call-count": 24,
      "total-time": 0.00516486,
      "time-per-call": 0.000215203,
      "kernel-type": "REGION"
    },
    {
      "kernel-name": "invert_map_by_atomics",
      "call-count": 12,
      "total-time": 0.00486493,
      "time-per-call": 0.000405411,
      "kernel-type": "REGION"
    },
    {
      "kernel-name": "array device to host",
      "call-count": 216,
      "total-time": 0.0046401,
      "time-per-call": 2.1482e-05,
      "kernel-type": "REGION"
    },
    {
      "kernel-name": "permute",
      "call-count": 48,
      "total-time": 0.00375414,
      "time-per-call": 7.82112e-05,
      "kernel-type": "REGION"
    },
    {
      "kernel-name": "expand",
      "call-count": 36,
      "total-time": 0.00364423,
      "time-per-call": 0.000101229,
      "kernel-type": "REGION"
    },
    {
      "kernel-name": "unmap",
      "call-count": 48,
      "total-time": 0.00307345,
      "time-per-call": 6.40303e-05,
      "kernel-type": "REGION"
    },
    {
      "kernel-name": "map_into",
      "call-count": 48,
      "total-time": 0.00282788,
      "time-per-call": 5.89142e-05,
      "kernel-type": "REGION"
    },
    {
      "kernel-name": "first barrier",
      "call-count": 12,
      "total-time": 0.00222325,
      "time-per-call": 0.000185271,
      "kernel-type": "REGION"
    },
    {
      "kernel-name": "expand_into",
      "call-count": 36,
      "total-time": 0.00194836,
      "time-per-call": 5.4121e-05,
      "kernel-type": "REGION"
    },
    {
      "kernel-name": "single device to host",
      "call-count": 80,
      "total-time": 0.00179839,
      "time-per-call": 2.24799e-05,
      "kernel-type": "REGION"
    },
    {
      "kernel-name": "fill_right",
      "call-count": 12,
      "total-time": 0.00145149,
      "time-per-call": 0.000120958,
      "kernel-type": "REGION"
    },
    {
      "kernel-name": "compound_maps",
      "call-count": 12,
      "total-time": 0.000972986,
      "time-per-call": 8.10822e-05,
      "kernel-type": "REGION"
    },
    {
      "kernel-name": "single host to device",
      "call-count": 64,
      "total-time": 0.000965357,
      "time-per-call": 1.50837e-05,
      "kernel-type": "REGION"
    },
    {
      "kernel-name": "Neighbor_alltoall",
      "call-count": 12,
      "total-time": 0.000288486,
      "time-per-call": 2.40405e-05,
      "kernel-type": "REGION"
    },
    {
      "kernel-name": "set_ents",
      "call-count": 8,
      "total-time": 5.4121e-05,
      "time-per-call": 6.76513e-06,
      "kernel-type": "REGION"
    }
  ],
  "kernel-data" : [
    {
      "kernel-name": "__nv_hdl_wrapper_t<false, false, false, __nv_dl_tag<int (*)(Omega_h::Read<int>, int, Omega_h::Write<int>), &(int Omega_h::number_same_values<int>(Omega_h::Read<int>, int, Omega_h::Write<int>)), 2u>, void (int, int&, bool), __nv_hdl_wrapper_t<false, false, false, __nv_dl_tag<int (*)(Omega_h::Read<int>, int, Omega_h::Write<int>), &(int Omega_h::number_same_values<int>(Omega_h::Read<int>, int, Omega_h::Write<int>)), 1u>, int (int), Omega_h::Read<int> const, int const>, Omega_h::Write<int> const>",
      "call-count": 20,
      "total-time": 0.0646832,
      "time-per-call": 0.00323416,
      "kernel-type": "PARALLEL_SCAN"
    },
    {
      "kernel-name": "__nv_hdl_wrapper_t<false, false, false, __nv_dl_tag<int (*)(Omega_h::Read<int>), &(int Omega_h::get_min<int>(Omega_h::Read<int>)), 1u>, void (int, int&), Omega_h::minimum<int> const, Omega_h::Read<int> >",
      "call-count": 12,
      "total-time": 0.0234962,
      "time-per-call": 0.00195801,
      "kernel-type": "PARALLEL_REDUCE"
    },
    {
      "kernel-name": "get_degrees",
      "call-count": 12,
      "total-time": 0.0063765,
      "time-per-call": 0.000531375,
      "kernel-type": "PARALLEL_FOR"
    },
    {
      "kernel-name": "Write(size,value)",
      "call-count": 52,
      "total-time": 0.00569415,
      "time-per-call": 0.000109503,
      "kernel-type": "PARALLEL_FOR"
    },
    {
      "kernel-name": "omegah_kk_offset_scan",
      "call-count": 24,
      "total-time": 0.0041945,
      "time-per-call": 0.000174771,
      "kernel-type": "PARALLEL_SCAN"
    },
    {
      "kernel-name": "__nv_hdl_wrapper_t<false, false, false, __nv_dl_tag<int (*)(Omega_h::Read<int>, int), &(int Omega_h::find_last<int>(Omega_h::Read<int>, int)), 2u>, void (int, int&), Omega_h::maximum<int> const, __nv_hdl_wrapper_t<false, false, false, __nv_dl_tag<int (*)(Omega_h::Read<int>, int), &(int Omega_h::find_last<int>(Omega_h::Read<int>, int)), 1u>, int (int), Omega_h::Read<int>, int> >",
      "call-count": 96,
      "total-time": 0.0026257,
      "time-per-call": 2.73511e-05,
      "kernel-type": "PARALLEL_REDUCE"
    },
    {
      "kernel-name": "__nv_hdl_wrapper_t<false, false, false, __nv_dl_tag<void (*)(Omega_h::Read<int>, Omega_h::Read<int>, Omega_h::Write<int>, int), &(void Omega_h::map_into<int>(Omega_h::Read<int>, Omega_h::Read<int>, Omega_h::Write<int>, int)), 1u>, void (int), Omega_h::Read<int>, int, Omega_h::Write<int>, Omega_h::Read<int> >",
      "call-count": 48,
      "total-time": 0.00128531,
      "time-per-call": 2.67774e-05,
      "kernel-type": "PARALLEL_FOR"
    },
    {
      "kernel-name": "omegah_kk_fill_right",
      "call-count": 12,
      "total-time": 0.00120664,
      "time-per-call": 0.000100553,
      "kernel-type": "PARALLEL_SCAN"
    },
    {
      "kernel-name": "__nv_hdl_wrapper_t<false, false, false, __nv_dl_tag<Omega_h::Write<int> (*)(Omega_h::Read<int>, Omega_h::Read<int>, int), &(Omega_h::Write<int> Omega_h::unmap<int>(Omega_h::Read<int>, Omega_h::Read<int>, int)), 1u>, void (int), Omega_h::Read<int>, int, Omega_h::Write<int>, Omega_h::Read<int> >",
      "call-count": 48,
      "total-time": 0.00114608,
      "time-per-call": 2.38766e-05,
      "kernel-type": "PARALLEL_FOR"
    },
    {
      "kernel-name": "__nv_hdl_wrapper_t<false, false, false, __nv_dl_tag<void (*)(Omega_h::Read<int>, Omega_h::Read<int>, Omega_h::Write<int>, int), &(void Omega_h::expand_into<int>(Omega_h::Read<int>, Omega_h::Read<int>, Omega_h::Write<int>, int)), 1u>, void (int), Omega_h::Read<int>, int, Omega_h::Write<int>, Omega_h::Read<int> >",
      "call-count": 36,
      "total-time": 0.000781775,
      "time-per-call": 2.1716e-05,
      "kernel-type": "PARALLEL_FOR"
    },
    {
      "kernel-name": "__nv_hdl_wrapper_t<false, false, false, __nv_dl_tag<void (*)(Omega_h::Read<int>, int, Omega_h::Write<int>, Omega_h::Write<int>, int), &(void Omega_h::combine_perms<int>(Omega_h::Read<int>, int, Omega_h::Write<int>, Omega_h::Write<int>, int)), 1u>, void (int), Omega_h::Read<int> const, int const, Omega_h::Write<int> const, Omega_h::Write<int> const, int>",
      "call-count": 20,
      "total-time": 0.000516176,
      "time-per-call": 2.58088e-05,
      "kernel-type": "PARALLEL_FOR"
    },
    {
      "kernel-name": "__nv_hdl_wrapper_t<false, false, false, __nv_dl_tag<Omega_h::Graph (*)(Omega_h::Read<int>, int, std::__cxx11::basic_string<char, std::char_traits<char>, std::allocator<char> > const&, std::__cxx11::basic_string<char, std::char_traits<char>, std::allocator<char> > const&), &Omega_h::invert_map_by_atomics, 2u>, void (int), Omega_h::Read<int> const, Omega_h::Read<int> const, Omega_h::Write<int> const, Omega_h::Write<int> >",
      "call-count": 12,
      "total-time": 0.000407696,
      "time-per-call": 3.39746e-05,
      "kernel-type": "PARALLEL_FOR"
    },
    {
      "kernel-name": "__nv_hdl_wrapper_t<false, false, false, __nv_dl_tag<Omega_h::Graph (*)(Omega_h::Read<int>, int, std::__cxx11::basic_string<char, std::char_traits<char>, std::allocator<char> > const&, std::__cxx11::basic_string<char, std::char_traits<char>, std::allocator<char> > const&), &Omega_h::invert_map_by_atomics, 1u>, void (int), Omega_h::Read<int> const, Omega_h::Write<int> >",
      "call-count": 12,
      "total-time": 0.000390291,
      "time-per-call": 3.25243e-05,
      "kernel-type": "PARALLEL_FOR"
    },
    {
      "kernel-name": "__nv_hdl_wrapper_t<false, false, false, __nv_dl_tag<Omega_h::Read<int> (*)(Omega_h::Read<int>, Omega_h::Read<int>), &Omega_h::compound_maps, 1u>, void (int), Omega_h::Read<int>, Omega_h::Read<int>, Omega_h::Write<int> >",
      "call-count": 12,
      "total-time": 0.000390291,
      "time-per-call": 3.25243e-05,
      "kernel-type": "PARALLEL_FOR"
    },
    {
      "kernel-name": "__nv_hdl_wrapper_t<false, false, false, __nv_dl_tag<int (*)(Omega_h::Read<int>, int), &(int Omega_h::next_smallest_value<int>(Omega_h::Read<int>, int)), 2u>, void (int, int&), Omega_h::minimum<int> const, __nv_hdl_wrapper_t<false, false, false, __nv_dl_tag<int (*)(Omega_h::Read<int>, int), &(int Omega_h::next_smallest_value<int>(Omega_h::Read<int>, int)), 1u>, int (int), Omega_h::Read<int> const, int const, int const> >",
      "call-count": 8,
      "total-time": 0.00026679,
      "time-per-call": 3.33488e-05,
      "kernel-type": "PARALLEL_REDUCE"
    },
    {
      "kernel-name": "invert_fan",
      "call-count": 12,
      "total-time": 0.000257492,
      "time-per-call": 2.14577e-05,
      "kernel-type": "PARALLEL_FOR"
    },
    {
      "kernel-name": "Kokkos::View::initialization [view] via memset",
      "call-count": 8,
      "total-time": 0.000118971,
      "time-per-call": 1.48714e-05,
      "kernel-type": "PARALLEL_FOR"
    }
  ]
}
